{
  "id": "45612388-2644-5f42-a3e7-330d43c4670d",
  "occurrenceDateTime": "2023-01-15",
  "patient": {
    "reference": "Patient/77b1da4d-6d76-5a21-ac84-5984e9465ff8"
  },
  "resourceType": "Immunization",
  "status": "completed",
  "vaccineCode": {
    "coding": [
      {
        "code": "207",
        "display": "COVID-19, mRNA, LNP-S, PF, 100 mcg/0.5mL dose or 50 mcg/0.25mL dose",
        "system": "http://hl7.org/fhir/sid/cvx"
      }
    ],
    "text": "COVID-19, mRNA, LNP-S, PF, 100 mcg/0.5mL dose or 50 mcg/0.25mL dose"
  }
}