{
  "category": [
    {
      "coding": [
        {
          "code": "problem-list-item",
          "system": "http://terminology.hl7.org/CodeSystem/condition-category"
        }
      ]
    }
  ],
  "clinicalStatus": {
    "coding": [
      {
        "code": "active",
        "system": "http://terminology.hl7.org/CodeSystem/condition-clinical"
      }
    ]
  },
  "code": {
    "coding": [
      {
        "code": "38341003",
        "display": "Hypertensive disorder",
        "system": "http://snomed.info/sct"
      }
    ],
    "text": "Hypertensive disorder"
  },
  "id": "cond-p-001-00",
  "recordedDate": "2023-04-15",
  "resourceType": "Condition",
  "subject": {
    "reference": "Patient/p-001"
  },
  "verificationStatus": {
    "coding": [
      {
        "code": "confirmed",
        "system": "http://terminology.hl7.org/CodeSystem/condition-ver-status"
      }
    ]
  }
}